{
  "cities": [
    {
      "id": 1,
      "name": "Alhambra",
      "firestation": "false"
    },
    {
      "id": 2,
      "name": "Barcelona",
      "firestation": "true"
    },
    {
      "id": 3,
      "name": "Cadiz",
      "firestation": "true"
    },
    {
      "id": 4,
      "name": "Darnius",
      "firestation": "false"
    }
  ],
  "roads": [
    {
      "id": 0,
      "cities": [
        "A",
        "B"
      ],
      "time": 2
    },
    {
      "id": 1,
      "cities": [
        "A",
        "C"
      ],
      "time": 3
    },
    {
      "id": 2,
      "cities": [
        "A",
        "D"
      ],
      "time": 4
    },
    {
      "id": 3,
      "cities": [
        "A",
        "E"
      ],
      "time": 1
    }
  ],
  "max_time": [
    {
      "time": 10
    }
  ]
}